<?xml version="1.0" encoding="UTF-8"?>
<site>
   <description url="http://updatesite.counterclockwise.googlecode.com/hg/">
      Counterclockwise Update Site. Counterclockwise is an Eclipse feature supporting the development of clojure code
   </description>
   <feature url="features/ccw.feature_0.0.38.jar" id="ccw.feature" version="0.0.38">
      <category name="Clojure Programming"/>
   </feature>
   <feature url="features/ccw.feature_0.0.39.jar" id="ccw.feature" version="0.0.39">
      <category name="Clojure Programming"/>
   </feature>
   <feature url="features/ccw.feature_0.0.40.jar" id="ccw.feature" version="0.0.40">
      <category name="Clojure Programming"/>
   </feature>
   <feature url="features/ccw.feature_0.0.41.jar" id="ccw.feature" version="0.0.41">
      <category name="Clojure Programming"/>
   </feature>
   <feature url="features/ccw.feature_0.0.42.jar" id="ccw.feature" version="0.0.42">
      <category name="Clojure Programming"/>
   </feature>
   <feature url="features/ccw.feature_0.0.43.jar" id="ccw.feature" version="0.0.43">
      <category name="Clojure Programming"/>
   </feature>
   <feature url="features/ccw.feature_0.0.44.jar" id="ccw.feature" version="0.0.44">
      <category name="Clojure Programming"/>
   </feature>
   <feature url="features/ccw.feature_0.0.45.jar" id="ccw.feature" version="0.0.45">
      <category name="Clojure Programming"/>
   </feature>
   <feature url="features/ccw.feature_0.0.46.jar" id="ccw.feature" version="0.0.46">
      <category name="Clojure Programming"/>
   </feature>
   <feature url="features/ccw.feature_0.0.48.jar" id="ccw.feature" version="0.0.48">
      <category name="Clojure Programming"/>
   </feature>
   <feature url="features/ccw.feature_0.0.49.stable.jar" id="ccw.feature" version="0.0.49.stable">
      <category name="Clojure Programming"/>
   </feature>
   <feature url="features/ccw.feature_0.0.50.STABLE.jar" id="ccw.feature" version="0.0.50.STABLE">
      <category name="Clojure Programming"/>
   </feature>
   <feature url="features/ccw.feature_0.0.51.STABLE.jar" id="ccw.feature" version="0.0.51.STABLE">
      <category name="Clojure Programming"/>
   </feature>
   <feature url="features/ccw.feature_0.0.52.STABLE.jar" id="ccw.feature" version="0.0.52.STABLE">
      <category name="Clojure Programming"/>
   </feature>
   <category-def name="Clojure Programming" label="Clojure Programming">
      <description>
         Clojure Programming tools and environments
      </description>
   </category-def>
</site>
